odoo/addons/fastapi_auth_jwt/README.rst
odoo/addons/fastapi_auth_jwt/__init__.py
odoo/addons/fastapi_auth_jwt/__manifest__.py
odoo/addons/fastapi_auth_jwt/dependencies.py
odoo/addons/fastapi_auth_jwt/i18n/fastapi_auth_jwt.pot
odoo/addons/fastapi_auth_jwt/i18n/it.po
odoo/addons/fastapi_auth_jwt/readme/DESCRIPTION.md
odoo/addons/fastapi_auth_jwt/readme/USAGE.md
odoo/addons/fastapi_auth_jwt/static/description/icon.png
odoo/addons/fastapi_auth_jwt/static/description/index.html
odoo_addon_fastapi_auth_jwt-18.0.1.0.0.3.dist-info/METADATA
odoo_addon_fastapi_auth_jwt-18.0.1.0.0.3.dist-info/WHEEL
odoo_addon_fastapi_auth_jwt-18.0.1.0.0.3.dist-info/top_level.txt
odoo_addon_fastapi_auth_jwt-18.0.1.0.0.3.dist-info/RECORD
