Metadata-Version: 2.1
Name: odoo-addon-fastapi_auth_jwt
Version: 18.0.1.0.0.3
Requires-Python: >=3.10
Requires-Dist: cryptography
Requires-Dist: odoo-addon-auth_jwt==18.0.*
Requires-Dist: odoo-addon-fastapi==18.0.*
Requires-Dist: odoo==18.0.*
Requires-Dist: pyjwt
Summary: JWT bearer token authentication for FastAPI.
Home-page: https://github.com/OCA/rest-framework
License: LGPL-3
Author: ACSONE SA/NV,Odoo Community Association (OCA)
Author-email: support@odoo-community.org
Classifier: Programming Language :: Python
Classifier: Framework :: Odoo
Classifier: Framework :: Odoo :: 18.0
Classifier: License :: OSI Approved :: GNU Lesser General Public License v3 (LGPLv3)
